run.py
src/cnd_eyes_injector/__init__.py
src/cnd_eyes_injector/__version__.py
src/cnd_eyes_injector/_app.py
src/cnd_eyes_injector/_base.py
src/cnd_eyes_injector/_cloud_account.py
src/cnd_eyes_injector/_customer.py
src/cnd_eyes_injector/_datacenter.py
src/cnd_eyes_injector/_deployment.py
src/cnd_eyes_injector/_domain.py
src/cnd_eyes_injector/_environment.py
src/cnd_eyes_injector/_environment_app.py
src/cnd_eyes_injector/_environment_infra.py
src/cnd_eyes_injector/_flavor.py
src/cnd_eyes_injector/_hostname.py
src/cnd_eyes_injector/_licenced_app.py
src/cnd_eyes_injector/_organization.py
src/cnd_eyes_injector/_os_type.py
src/cnd_eyes_injector/_project.py
src/cnd_eyes_injector/_service.py
src/cnd_eyes_injector/_software.py
src/cnd_eyes_injector/_source.py
src/cnd_eyes_injector/_tier.py
src/cnd_eyes_injector/_vm.py
src/cnd_eyes_injector/_vm_tag.py
src/cnd_eyes_injector/adapter.py
src/cnd_eyes_injector/eyes_injector.py
cndeyesinjector-0.0.3.dist-info/METADATA
cndeyesinjector-0.0.3.dist-info/WHEEL
cndeyesinjector-0.0.3.dist-info/RECORD
